shifu/__init__.py
shifu/shifu.py
shifu/core/__init__.py
shifu/core/enums.py
shifu/core/shell.py
shifu/core/para/__init__.py
shifu/core/tests/__init__.py
shifu/java/.DS_Store
shifu/java/__init__.py
shifu/java/bin/.DS_Store
shifu/java/bin/__init__.py
shifu/java/bin/driver_test.sh
shifu/java/bin/shifu
shifu/java/bin/shifu_bash_completion.sh
shifu/java/bin/shifutest
shifu/java/bin/data-model/.HEAD
shifu/java/bin/data-model/ModelConfig.json
shifu/java/bin/data-model/__init__.py
shifu/java/bin/data-model/columns/Eval1.meta.column.names
shifu/java/bin/data-model/columns/Eval1score.meta.column.names
shifu/java/bin/data-model/columns/__init__.py
shifu/java/bin/data-model/columns/categorical.column.names
shifu/java/bin/data-model/columns/forceremove.column.names
shifu/java/bin/data-model/columns/forceselect.column.names
shifu/java/bin/data-model/columns/meta.column.names
shifu/java/bin/logs/__init__.py
shifu/java/bin/logs/shifu.log
shifu/java/bin/logs/zookeeper.log
shifu/java/conf/__init__.py
shifu/java/conf/shifuconfig
shifu/java/example/__init__.py
shifu/java/example/cancer-judgement/DataStore/DataSet1/.pig_header
shifu/java/example/cancer-judgement/DataStore/DataSet1/part-00
shifu/java/example/cancer-judgement/DataStore/EvalSet1/.pig_header
shifu/java/example/cancer-judgement/DataStore/EvalSet1/part-00
shifu/java/example/cancer-judgement/DataStore/Full_data/data.dat
shifu/java/example/cancer-judgement/ModelStore/ModelSet1/ColumnConfig.json
shifu/java/example/cancer-judgement/ModelStore/ModelSet1/ModelConfig.json
shifu/java/example/cancer-judgement/ModelStore/ModelSet1/pr_curve.xlsx
shifu/java/example/cancer-judgement/ModelStore/ModelSet2/ColumnConfig.json
shifu/java/example/cancer-judgement/ModelStore/ModelSet2/ModelConfig.json
shifu/java/example/cancer-judgement/ModelStore/ModelSet3/ColumnConfig.json
shifu/java/example/cancer-judgement/ModelStore/ModelSet3/ModelConfig.json
shifu/java/lib/__init__.py
shifu-1.0.6.dist-info/DESCRIPTION.rst
shifu-1.0.6.dist-info/METADATA
shifu-1.0.6.dist-info/RECORD
shifu-1.0.6.dist-info/WHEEL
shifu-1.0.6.dist-info/metadata.json
shifu-1.0.6.dist-info/top_level.txt
