Metadata-Version: 2.0
Name: shifu
Version: 1.0.6
Summary: An end-to-end machine learning and data mining framework on Hadoop.
Home-page: https://github.com/wuhaifengdhu/python-shifu
Author: Wu Haifeng
Author-email: wuhaifengdhu@163.com
License: UNKNOWN
Platform: UNKNOWN
Requires-Dist: six (>=1.10.0)
